<annotation>
	<folder>新麦26</folder>
	<filename>00033.jpg</filename>
	<path>D:\工作\新麦26\00033.jpg</path>
	<source>
		<database>Unknown</database>
	</source>
	<size>
		<width>4248</width>
		<height>2528</height>
		<depth>3</depth>
	</size>
	<segmented>0</segmented>
	<object>
		<name>wheat</name>
		<pose>Unspecified</pose>
		<truncated>0</truncated>
		<difficult>0</difficult>
		<bndbox>
			<xmin>163</xmin>
			<ymin>1158</ymin>
			<xmax>206</xmax>
			<ymax>1359</ymax>
		</bndbox>
	</object>
	<object>
		<name>wheat</name>
		<pose>Unspecified</pose>
		<truncated>0</truncated>
		<difficult>0</difficult>
		<bndbox>
			<xmin>504</xmin>
			<ymin>1097</ymin>
			<xmax>552</xmax>
			<ymax>1180</ymax>
		</bndbox>
	</object>
	<object>
		<name>wheat</name>
		<pose>Unspecified</pose>
		<truncated>0</truncated>
		<difficult>0</difficult>
		<bndbox>
			<xmin>862</xmin>
			<ymin>1074</ymin>
			<xmax>929</xmax>
			<ymax>1272</ymax>
		</bndbox>
	</object>
	<object>
		<name>wheat</name>
		<pose>Unspecified</pose>
		<truncated>0</truncated>
		<difficult>0</difficult>
		<bndbox>
			<xmin>965</xmin>
			<ymin>1152</ymin>
			<xmax>1027</xmax>
			<ymax>1323</ymax>
		</bndbox>
	</object>
	<object>
		<name>wheat</name>
		<pose>Unspecified</pose>
		<truncated>0</truncated>
		<difficult>0</difficult>
		<bndbox>
			<xmin>1126</xmin>
			<ymin>998</ymin>
			<xmax>1194</xmax>
			<ymax>1124</ymax>
		</bndbox>
	</object>
	<object>
		<name>wheat</name>
		<pose>Unspecified</pose>
		<truncated>0</truncated>
		<difficult>0</difficult>
		<bndbox>
			<xmin>1373</xmin>
			<ymin>1095</ymin>
			<xmax>1441</xmax>
			<ymax>1265</ymax>
		</bndbox>
	</object>
	<object>
		<name>wheat</name>
		<pose>Unspecified</pose>
		<truncated>0</truncated>
		<difficult>0</difficult>
		<bndbox>
			<xmin>1471</xmin>
			<ymin>978</ymin>
			<xmax>1520</xmax>
			<ymax>1178</ymax>
		</bndbox>
	</object>
	<object>
		<name>wheat</name>
		<pose>Unspecified</pose>
		<truncated>0</truncated>
		<difficult>0</difficult>
		<bndbox>
			<xmin>1608</xmin>
			<ymin>1018</ymin>
			<xmax>1641</xmax>
			<ymax>1217</ymax>
		</bndbox>
	</object>
	<object>
		<name>wheat</name>
		<pose>Unspecified</pose>
		<truncated>0</truncated>
		<difficult>0</difficult>
		<bndbox>
			<xmin>1776</xmin>
			<ymin>1039</ymin>
			<xmax>1816</xmax>
			<ymax>1174</ymax>
		</bndbox>
	</object>
	<object>
		<name>wheat</name>
		<pose>Unspecified</pose>
		<truncated>0</truncated>
		<difficult>0</difficult>
		<bndbox>
			<xmin>2232</xmin>
			<ymin>947</ymin>
			<xmax>2295</xmax>
			<ymax>1135</ymax>
		</bndbox>
	</object>
	<object>
		<name>wheat</name>
		<pose>Unspecified</pose>
		<truncated>0</truncated>
		<difficult>0</difficult>
		<bndbox>
			<xmin>2779</xmin>
			<ymin>1124</ymin>
			<xmax>2840</xmax>
			<ymax>1335</ymax>
		</bndbox>
	</object>
	<object>
		<name>wheat</name>
		<pose>Unspecified</pose>
		<truncated>0</truncated>
		<difficult>0</difficult>
		<bndbox>
			<xmin>3175</xmin>
			<ymin>1203</ymin>
			<xmax>3215</xmax>
			<ymax>1300</ymax>
		</bndbox>
	</object>
	<object>
		<name>wheat</name>
		<pose>Unspecified</pose>
		<truncated>0</truncated>
		<difficult>0</difficult>
		<bndbox>
			<xmin>3439</xmin>
			<ymin>869</ymin>
			<xmax>3491</xmax>
			<ymax>1049</ymax>
		</bndbox>
	</object>
	<object>
		<name>wheat</name>
		<pose>Unspecified</pose>
		<truncated>0</truncated>
		<difficult>0</difficult>
		<bndbox>
			<xmin>3547</xmin>
			<ymin>1037</ymin>
			<xmax>3609</xmax>
			<ymax>1201</ymax>
		</bndbox>
	</object>
	<object>
		<name>wheat</name>
		<pose>Unspecified</pose>
		<truncated>0</truncated>
		<difficult>0</difficult>
		<bndbox>
			<xmin>3998</xmin>
			<ymin>1051</ymin>
			<xmax>4071</xmax>
			<ymax>1315</ymax>
		</bndbox>
	</object>
</annotation>
