<annotation>
	<folder>新麦26</folder>
	<filename>00008.jpg</filename>
	<path>D:\工作\新麦26\00008.jpg</path>
	<source>
		<database>Unknown</database>
	</source>
	<size>
		<width>4248</width>
		<height>2528</height>
		<depth>3</depth>
	</size>
	<segmented>0</segmented>
	<object>
		<name>wheat</name>
		<pose>Unspecified</pose>
		<truncated>0</truncated>
		<difficult>0</difficult>
		<bndbox>
			<xmin>134</xmin>
			<ymin>984</ymin>
			<xmax>228</xmax>
			<ymax>1205</ymax>
		</bndbox>
	</object>
	<object>
		<name>wheat</name>
		<pose>Unspecified</pose>
		<truncated>0</truncated>
		<difficult>0</difficult>
		<bndbox>
			<xmin>263</xmin>
			<ymin>1001</ymin>
			<xmax>343</xmax>
			<ymax>1286</ymax>
		</bndbox>
	</object>
	<object>
		<name>wheat</name>
		<pose>Unspecified</pose>
		<truncated>0</truncated>
		<difficult>0</difficult>
		<bndbox>
			<xmin>947</xmin>
			<ymin>1082</ymin>
			<xmax>1015</xmax>
			<ymax>1192</ymax>
		</bndbox>
	</object>
	<object>
		<name>wheat</name>
		<pose>Unspecified</pose>
		<truncated>0</truncated>
		<difficult>0</difficult>
		<bndbox>
			<xmin>1117</xmin>
			<ymin>1108</ymin>
			<xmax>1184</xmax>
			<ymax>1266</ymax>
		</bndbox>
	</object>
	<object>
		<name>wheat</name>
		<pose>Unspecified</pose>
		<truncated>0</truncated>
		<difficult>0</difficult>
		<bndbox>
			<xmin>1730</xmin>
			<ymin>1029</ymin>
			<xmax>1819</xmax>
			<ymax>1218</ymax>
		</bndbox>
	</object>
	<object>
		<name>wheat</name>
		<pose>Unspecified</pose>
		<truncated>0</truncated>
		<difficult>0</difficult>
		<bndbox>
			<xmin>1608</xmin>
			<ymin>1075</ymin>
			<xmax>1676</xmax>
			<ymax>1201</ymax>
		</bndbox>
	</object>
	<object>
		<name>wheat</name>
		<pose>Unspecified</pose>
		<truncated>0</truncated>
		<difficult>0</difficult>
		<bndbox>
			<xmin>2000</xmin>
			<ymin>990</ymin>
			<xmax>2097</xmax>
			<ymax>1238</ymax>
		</bndbox>
	</object>
	<object>
		<name>wheat</name>
		<pose>Unspecified</pose>
		<truncated>0</truncated>
		<difficult>0</difficult>
		<bndbox>
			<xmin>1454</xmin>
			<ymin>1049</ymin>
			<xmax>1504</xmax>
			<ymax>1192</ymax>
		</bndbox>
	</object>
	<object>
		<name>wheat</name>
		<pose>Unspecified</pose>
		<truncated>0</truncated>
		<difficult>0</difficult>
		<bndbox>
			<xmin>2554</xmin>
			<ymin>1010</ymin>
			<xmax>2630</xmax>
			<ymax>1245</ymax>
		</bndbox>
	</object>
	<object>
		<name>wheat</name>
		<pose>Unspecified</pose>
		<truncated>0</truncated>
		<difficult>0</difficult>
		<bndbox>
			<xmin>2689</xmin>
			<ymin>1003</ymin>
			<xmax>2756</xmax>
			<ymax>1214</ymax>
		</bndbox>
	</object>
	<object>
		<name>wheat</name>
		<pose>Unspecified</pose>
		<truncated>0</truncated>
		<difficult>0</difficult>
		<bndbox>
			<xmin>2826</xmin>
			<ymin>951</ymin>
			<xmax>2906</xmax>
			<ymax>1218</ymax>
		</bndbox>
	</object>
	<object>
		<name>wheat</name>
		<pose>Unspecified</pose>
		<truncated>0</truncated>
		<difficult>0</difficult>
		<bndbox>
			<xmin>2939</xmin>
			<ymin>1010</ymin>
			<xmax>3026</xmax>
			<ymax>1284</ymax>
		</bndbox>
	</object>
	<object>
		<name>wheat</name>
		<pose>Unspecified</pose>
		<truncated>0</truncated>
		<difficult>0</difficult>
		<bndbox>
			<xmin>3076</xmin>
			<ymin>962</ymin>
			<xmax>3154</xmax>
			<ymax>1192</ymax>
		</bndbox>
	</object>
	<object>
		<name>wheat</name>
		<pose>Unspecified</pose>
		<truncated>0</truncated>
		<difficult>0</difficult>
		<bndbox>
			<xmin>3186</xmin>
			<ymin>1034</ymin>
			<xmax>3241</xmax>
			<ymax>1245</ymax>
		</bndbox>
	</object>
	<object>
		<name>wheat</name>
		<pose>Unspecified</pose>
		<truncated>0</truncated>
		<difficult>0</difficult>
		<bndbox>
			<xmin>3356</xmin>
			<ymin>1016</ymin>
			<xmax>3486</xmax>
			<ymax>1266</ymax>
		</bndbox>
	</object>
	<object>
		<name>wheat</name>
		<pose>Unspecified</pose>
		<truncated>0</truncated>
		<difficult>0</difficult>
		<bndbox>
			<xmin>3545</xmin>
			<ymin>923</ymin>
			<xmax>3626</xmax>
			<ymax>1175</ymax>
		</bndbox>
	</object>
	<object>
		<name>wheat</name>
		<pose>Unspecified</pose>
		<truncated>0</truncated>
		<difficult>0</difficult>
		<bndbox>
			<xmin>3993</xmin>
			<ymin>912</ymin>
			<xmax>4093</xmax>
			<ymax>1201</ymax>
		</bndbox>
	</object>
	<object>
		<name>wheat</name>
		<pose>Unspecified</pose>
		<truncated>0</truncated>
		<difficult>0</difficult>
		<bndbox>
			<xmin>3647</xmin>
			<ymin>975</ymin>
			<xmax>3723</xmax>
			<ymax>1218</ymax>
		</bndbox>
	</object>
	<object>
		<name>wheat</name>
		<pose>Unspecified</pose>
		<truncated>0</truncated>
		<difficult>0</difficult>
		<bndbox>
			<xmin>2234</xmin>
			<ymin>1216</ymin>
			<xmax>2360</xmax>
			<ymax>1410</ymax>
		</bndbox>
	</object>
	<object>
		<name>wheat</name>
		<pose>Unspecified</pose>
		<truncated>0</truncated>
		<difficult>0</difficult>
		<bndbox>
			<xmin>2239</xmin>
			<ymin>929</ymin>
			<xmax>2319</xmax>
			<ymax>1142</ymax>
		</bndbox>
	</object>
	<object>
		<name>wheat</name>
		<pose>Unspecified</pose>
		<truncated>0</truncated>
		<difficult>0</difficult>
		<bndbox>
			<xmin>839</xmin>
			<ymin>1118</ymin>
			<xmax>906</xmax>
			<ymax>1251</ymax>
		</bndbox>
	</object>
	<object>
		<name>wheat</name>
		<pose>Unspecified</pose>
		<truncated>1</truncated>
		<difficult>0</difficult>
		<bndbox>
			<xmin>4158</xmin>
			<ymin>1021</ymin>
			<xmax>4248</xmax>
			<ymax>1251</ymax>
		</bndbox>
	</object>
</annotation>
